{"disqus":{"path":"/web/nursery-rhyme-code-poem-css/","commentCount":1,"comments":[{"postId":"1989478525","parentPostId":null,"date":"2015-04-27T06:51:32Z","author":"Ronnie","avatar":"https://www.gravatar.com/avatar/5de3283a14ac872c97340035a1410a94?d=mm&s=60","message":"<p>Have your kids seen this nursery rhymes video: <a href=\"https://www.youtube.com/watch?v=xZUdN0t19TU\" rel=\"nofollow noopener\" title=\"https://www.youtube.com/watch?v=xZUdN0t19TU\">https://www.youtube.com/wat...</a></p>","replies":[]}]}}